tprogress/__init__.py
tprogress/tprogress.py
tprogress-0.0.6.dist-info/LICENSE
tprogress-0.0.6.dist-info/METADATA
tprogress-0.0.6.dist-info/WHEEL
tprogress-0.0.6.dist-info/top_level.txt
tprogress-0.0.6.dist-info/RECORD
