Metadata-Version: 2.1
Name: tprogress
Version: 0.0.6
Summary: time monitoring
Home-page: https://github.com/thhapke/tprogress
Author: Thorsten Hapke
Author-email: thorsten.hapke@sap.com
License: UNKNOWN
Keywords: time keeping,time monitoring
Platform: UNKNOWN
Classifier: Programming Language :: Python :: 3.5
Classifier: Programming Language :: Python :: 3.6
Classifier: Programming Language :: Python :: 3.7
Classifier: License :: OSI Approved :: MIT License
Classifier: Operating System :: OS Independent
